<?xml version="1.0" encoding="utf-8" ?>
<dwsync>
<file name="default.asp" server="wmsistema10.com.br/prova/levi/" local="130395431759962237" remote="130395434400000000" Dst="1" />
<file name="curso_inserir.asp" server="wmsistema10.com.br/prova/levi/" local="130299758696298952" remote="130299758400000000" Dst="2" />
<file name="estilo.css" server="wmsistema10.com.br/prova/levi/" local="130299427579576779" remote="130299427200000000" Dst="2" />
<file name="curso_inserir_script.asp" server="wmsistema10.com.br/prova/levi/" local="130299737955630091" remote="130299737400000000" Dst="2" />
<file name="aluno_inserir.asp" server="wmsistema10.com.br/prova/levi/" local="130299641410000000" remote="130299640800000000" Dst="2" />
<file name="aluno_inserir_script.asp" server="wmsistema10.com.br/prova/levi/" local="130299738090830091" remote="130299738000000000" Dst="2" />
<file name="aluno_atualizar.asp" server="wmsistema10.com.br/prova/levi/" local="130299759655161452" remote="130299759000000000" Dst="2" />
<file name="aluno_atualizar_script.asp" server="wmsistema10.com.br/prova/levi/" local="130299756880866452" remote="130299756600000000" Dst="2" />
</dwsync>